codes/Armazenamento.py
codes/Consulta.py
codes/Interacao.py
codes/__init__.py
codes/main.py
trabalhoPacotes-0.0.1.dist-info/LICENSE
trabalhoPacotes-0.0.1.dist-info/METADATA
trabalhoPacotes-0.0.1.dist-info/WHEEL
trabalhoPacotes-0.0.1.dist-info/top_level.txt
trabalhoPacotes-0.0.1.dist-info/RECORD
