Metadata-Version: 2.1
Name: trabalhoPacotes
Version: 0.0.1
Summary: Pacote python para cadastro de usuários e consulta por cpf
Home-page: https://github.com/Ninniet5670/trabalhp-MyPy
Author: Marco Aurélio Proença Neto
Author-email: marconeto3000@gmail.com
License: MIT License
Keywords: Pacote
Platform: UNKNOWN
License-File: LICENSE
